ourskyai_platform_api/__init__.py
ourskyai_platform_api/api_client.py
ourskyai_platform_api/api_response.py
ourskyai_platform_api/configuration.py
ourskyai_platform_api/exceptions.py
ourskyai_platform_api/py.typed
ourskyai_platform_api/rest.py
ourskyai_platform_api/api/__init__.py
ourskyai_platform_api/api/default_api.py
ourskyai_platform_api/models/__init__.py
ourskyai_platform_api/models/camera_mode.py
ourskyai_platform_api/models/empty_success.py
ourskyai_platform_api/models/filter_type.py
ourskyai_platform_api/models/fits_header.py
ourskyai_platform_api/models/image_set_type.py
ourskyai_platform_api/models/location.py
ourskyai_platform_api/models/metric_type.py
ourskyai_platform_api/models/model_type.py
ourskyai_platform_api/models/mount_type.py
ourskyai_platform_api/models/network_interface.py
ourskyai_platform_api/models/node_state.py
ourskyai_platform_api/models/optical_tube_type.py
ourskyai_platform_api/models/orbit_type.py
ourskyai_platform_api/models/pki_certificate.py
ourskyai_platform_api/models/plate_solve_parameters.py
ourskyai_platform_api/models/shutter_type.py
ourskyai_platform_api/models/successful_create.py
ourskyai_platform_api/models/tracking_type.py
ourskyai_platform_api/models/upload_priority.py
ourskyai_platform_api/models/v1_all_sky_camera_config.py
ourskyai_platform_api/models/v1_all_sky_prediction.py
ourskyai_platform_api/models/v1_all_sky_prediction_label.py
ourskyai_platform_api/models/v1_apex_charts_timeline.py
ourskyai_platform_api/models/v1_apex_charts_timeline_element.py
ourskyai_platform_api/models/v1_asset_size.py
ourskyai_platform_api/models/v1_auto_focus_instruction.py
ourskyai_platform_api/models/v1_auto_focus_instruction_coordinates_inner.py
ourskyai_platform_api/models/v1_blackout_box.py
ourskyai_platform_api/models/v1_camera.py
ourskyai_platform_api/models/v1_camera_roll_image.py
ourskyai_platform_api/models/v1_client_token.py
ourskyai_platform_api/models/v1_complete_node_controller_crash_report_request.py
ourskyai_platform_api-1.3.9356.dist-info/METADATA
ourskyai_platform_api-1.3.9356.dist-info/WHEEL
ourskyai_platform_api-1.3.9356.dist-info/top_level.txt
ourskyai_platform_api-1.3.9356.dist-info/RECORD
