Metadata-Version: 2.4
Name: ourskyai-platform-api
Version: 1.3.9356
Summary: OurSky Platform
Home-page: 
Author: OpenAPI Generator community
Author-email: team@openapitools.org
Keywords: OpenAPI,OpenAPI-Generator,OurSky Platform
Requires-Dist: urllib3<2.1.0,>=1.25.3
Requires-Dist: python-dateutil
Requires-Dist: pydantic<2,>=1.10.5
Requires-Dist: aenum
Dynamic: author
Dynamic: author-email
Dynamic: description
Dynamic: description-content-type
Dynamic: keywords
Dynamic: requires-dist
Dynamic: summary
